common/__init__.py
workspace_qdrant_mcp/__init__.py
workspace_qdrant_mcp/http_server.py
workspace_qdrant_mcp/main.py
workspace_qdrant_mcp/server.py
workspace_qdrant_mcp-0.3.0.dist-info/licenses/LICENSE
wqm_cli/__init__.py
wqm_cli/cli_wrapper.py
workspace_qdrant_mcp-0.3.0.dist-info/METADATA
workspace_qdrant_mcp-0.3.0.dist-info/WHEEL
workspace_qdrant_mcp-0.3.0.dist-info/entry_points.txt
workspace_qdrant_mcp-0.3.0.dist-info/top_level.txt
workspace_qdrant_mcp-0.3.0.dist-info/RECORD
