Metadata-Version: 2.4
Name: workspace-qdrant-mcp
Version: 0.3.0
Summary: Project-scoped Qdrant MCP server with scratchbook functionality
Author-email: "Christian C. Berclaz" <christian.berclaz@mac.com>
License: MIT
Project-URL: Homepage, https://github.com/ChrisGVE/workspace-qdrant-mcp
Project-URL: Repository, https://github.com/ChrisGVE/workspace-qdrant-mcp
Project-URL: Issues, https://github.com/ChrisGVE/workspace-qdrant-mcp/issues
Project-URL: Changelog, https://github.com/ChrisGVE/workspace-qdrant-mcp/blob/main/CHANGELOG.md
Requires-Python: >=3.10
License-File: LICENSE
Requires-Dist: fastmcp>=0.3.0
Requires-Dist: qdrant-client>=1.7.0
Requires-Dist: fastembed>=0.2.0
Requires-Dist: GitPython>=3.1.0
Requires-Dist: pydantic>=2.0.0
Requires-Dist: pydantic-settings>=2.0.0
Requires-Dist: python-dotenv>=1.0.0
Requires-Dist: typer>=0.9.0
Requires-Dist: PyYAML>=6.0.0
Requires-Dist: rich>=13.0.0
Requires-Dist: chardet>=5.0.0
Requires-Dist: pypdf>=4.0.0
Requires-Dist: psutil>=5.8.0
Requires-Dist: tqdm>=4.67.1
Requires-Dist: grpcio>=1.60.0
Requires-Dist: grpcio-tools>=1.60.0
Requires-Dist: fastapi>=0.104.0
Requires-Dist: uvicorn>=0.24.0
Requires-Dist: jinja2>=3.1.0
Requires-Dist: python-multipart>=0.0.6
Requires-Dist: python-docx>=1.1.0
Requires-Dist: python-pptx>=0.6.23
Requires-Dist: ebooklib>=0.18
Requires-Dist: python-magic>=0.4.27
Requires-Dist: beautifulsoup4>=4.12.0
Requires-Dist: lxml>=4.9.0
Requires-Dist: markdown>=3.5.0
Requires-Dist: pygments>=2.16.0
Requires-Dist: loguru>=0.7.0
Requires-Dist: cachetools>=5.3.0
Requires-Dist: aiohttp>=3.9.0
Requires-Dist: aiofiles>=23.0.0
Requires-Dist: tldextract>=5.0.0
Requires-Dist: xxhash>=3.0.0
Requires-Dist: maturin>=1.9.4
Requires-Dist: toml>=0.10.0
Requires-Dist: watchdog>=3.0.0
Requires-Dist: fuzzywuzzy>=0.18.0
Requires-Dist: python-levenshtein>=0.20.0
Requires-Dist: playwright>=1.55.0
Requires-Dist: tabulate>=0.9.0
Provides-Extra: dev
Requires-Dist: pytest>=7.0.0; extra == "dev"
Requires-Dist: pytest-asyncio>=0.21.0; extra == "dev"
Requires-Dist: pytest-mock>=3.11.0; extra == "dev"
Requires-Dist: pytest-cov>=4.1.0; extra == "dev"
Requires-Dist: pytest-xdist>=3.3.0; extra == "dev"
Requires-Dist: pytest-timeout>=2.1.0; extra == "dev"
Requires-Dist: pytest-benchmark>=4.0.0; extra == "dev"
Requires-Dist: testcontainers>=3.7.0; extra == "dev"
Requires-Dist: httpx>=0.24.0; extra == "dev"
Requires-Dist: respx>=0.20.0; extra == "dev"
Requires-Dist: black>=23.0.0; extra == "dev"
Requires-Dist: ruff>=0.1.0; extra == "dev"
Requires-Dist: mypy>=1.0.0; extra == "dev"
Requires-Dist: pydocstyle>=6.0.0; extra == "dev"
Requires-Dist: docstring-parser>=0.15; extra == "dev"
Requires-Dist: scikit-learn>=1.0.0; extra == "dev"
Requires-Dist: rank-bm25>=0.2.2; extra == "dev"
Requires-Dist: nltk>=3.8.1; extra == "dev"
Requires-Dist: playwright>=1.40.0; extra == "dev"
Requires-Dist: pytest-playwright>=0.4.0; extra == "dev"
Requires-Dist: hypothesis>=6.0.0; extra == "dev"
Requires-Dist: tox>=4.0.0; extra == "dev"
Requires-Dist: packaging>=23.0; extra == "dev"
Requires-Dist: types-PyYAML>=6.0.0; extra == "dev"
Requires-Dist: types-Markdown>=3.4.0; extra == "dev"
Requires-Dist: types-psutil>=5.8.0; extra == "dev"
Provides-Extra: full
Requires-Dist: markdown>=3.4.0; extra == "full"
Requires-Dist: PyYAML>=6.0.0; extra == "full"
Requires-Dist: pypdf>=4.0.0; extra == "full"
Provides-Extra: tokenizers
Requires-Dist: tiktoken>=0.5.0; extra == "tokenizers"
Requires-Dist: transformers>=4.35.0; extra == "tokenizers"
Dynamic: license-file
